odoo/addons/storage_media_product/README.rst
odoo/addons/storage_media_product/__init__.py
odoo/addons/storage_media_product/__manifest__.py
odoo/addons/storage_media_product/i18n/it.po
odoo/addons/storage_media_product/i18n/storage_media_product.pot
odoo/addons/storage_media_product/models/__init__.py
odoo/addons/storage_media_product/models/product.py
odoo/addons/storage_media_product/models/product_category.py
odoo/addons/storage_media_product/readme/CONTRIBUTORS.md
odoo/addons/storage_media_product/readme/CREDITS.md
odoo/addons/storage_media_product/readme/DESCRIPTION.md
odoo/addons/storage_media_product/readme/HISTORY.md
odoo/addons/storage_media_product/readme/USAGE.md
odoo/addons/storage_media_product/security/ir.model.access.csv
odoo/addons/storage_media_product/static/description/icon.png
odoo/addons/storage_media_product/static/description/index.html
odoo/addons/storage_media_product/views/product.xml
odoo/addons/storage_media_product/views/product_category.xml
odoo_addon_storage_media_product-18.0.1.0.0.4.dist-info/METADATA
odoo_addon_storage_media_product-18.0.1.0.0.4.dist-info/WHEEL
odoo_addon_storage_media_product-18.0.1.0.0.4.dist-info/top_level.txt
odoo_addon_storage_media_product-18.0.1.0.0.4.dist-info/RECORD
